trieve/__init__.py
trieve/api.py
trieve/cli.py
trieve/config.py
trieve/db.py
trieve/main.py
trieve-0.2.0.dist-info/METADATA
trieve-0.2.0.dist-info/WHEEL
trieve-0.2.0.dist-info/entry_points.txt
trieve-0.2.0.dist-info/RECORD
